duckql/__init__.py
duckql/base.py
duckql/cli.py
duckql/exceptions.py
duckql/factory.py
duckql/utils.py
duckql/version.py
duckql/functions/__init__.py
duckql/functions/array_agg.py
duckql/functions/avg.py
duckql/functions/base.py
duckql/functions/concat.py
duckql/functions/convert_timezone.py
duckql/functions/count.py
duckql/functions/current_date.py
duckql/functions/date_add.py
duckql/functions/date_format.py
duckql/functions/date_sub.py
duckql/functions/extract.py
duckql/functions/first_value.py
duckql/functions/group_concat.py
duckql/functions/initcap.py
duckql/functions/lower.py
duckql/functions/min_max.py
duckql/functions/now.py
duckql/functions/string_agg.py
duckql/functions/sum.py
duckql/functions/to_char.py
duckql/functions/to_date.py
duckql/functions/unaccent.py
duckql/functions/upper.py
duckql/functions/weekday.py
duckql/properties/__init__.py
duckql/properties/array.py
duckql/properties/boolean.py
duckql/properties/constant.py
duckql/properties/null.py
duckql/properties/property.py
duckql/structures/__init__.py
duckql/structures/between.py
duckql/structures/case.py
duckql/structures/cast_operator.py
duckql/structures/comparision.py
duckql/structures/distinct.py
duckql/structures/interval.py
duckql/structures/join.py
duckql/structures/limit.py
duckql/structures/operator.py
duckql/structures/order.py
duckql/structures/query.py
duckql-0.14.0.dist-info/LICENSE
duckql-0.14.0.dist-info/METADATA
duckql-0.14.0.dist-info/WHEEL
duckql-0.14.0.dist-info/entry_points.txt
duckql-0.14.0.dist-info/top_level.txt
duckql-0.14.0.dist-info/RECORD
