Metadata-Version: 2.2
Name: duckql
Version: 0.14.0
Summary: JSON declarative SQL conversion library
Home-page: https://github.com/Sibyx/duckql-python
Author: Jakub Dubec
Author-email: jakub.dubec@gmail.com
License: MIT
Classifier: Development Status :: 4 - Beta
Classifier: Environment :: Console
Classifier: Programming Language :: Python
Classifier: Programming Language :: Python :: 3.9
Classifier: Programming Language :: Python :: 3.10
Classifier: Programming Language :: Python :: 3.11
Classifier: Programming Language :: Python :: Implementation :: PyPy
Classifier: Intended Audience :: Developers
Classifier: License :: OSI Approved :: MIT License
Classifier: Topic :: Database
Classifier: Topic :: Software Development :: Libraries
License-File: LICENSE
Requires-Dist: pydantic==1.*
Requires-Dist: click==8.*
Requires-Dist: typing-extensions
Dynamic: author
Dynamic: author-email
Dynamic: classifier
Dynamic: description
Dynamic: description-content-type
Dynamic: home-page
Dynamic: license
Dynamic: requires-dist
Dynamic: summary
